virulencefinder-3.2.0.dist-info/METADATA
virulencefinder-3.2.0.dist-info/WHEEL
virulencefinder-3.2.0.dist-info/entry_points.txt
virulencefinder-3.2.0.dist-info/licenses/LICENSE
virulencefinder/__init__.py
virulencefinder/__main__.py
virulencefinder/cge/__init__.py
virulencefinder/cge/config.py
virulencefinder/cge/dbconfig.py
virulencefinder/cge/environment_variables.md
virulencefinder/cge/exceptions.py
virulencefinder/cge/gene_result.py
virulencefinder/cge/get_input_data.py
virulencefinder/cge/phenotype_scraping.py
virulencefinder/cge/process_results_json.py
virulencefinder/helper_scripts/__init__.py
virulencefinder/helper_scripts/alignment_.py
virulencefinder/helper_scripts/create_table.py
virulencefinder/helper_scripts/file_transformations_.py
virulencefinder/helper_scripts/old_json_results.py
virulencefinder/helper_scripts/parser.py
virulencefinder/helper_scripts/software_executions.py
virulencefinder-3.2.0.dist-info/RECORD
