Metadata-Version: 2.1
Name: Virulencefinder
Version: 3.2.0
Summary: Finds virulence genes in ngs samples based on databases for several organisms
Author-Email: Center for Genomic Epidemiology <food-cgehelp@dtu.dk>
License: Apache-2.0
Requires-Python: >=3.10
Requires-Dist: tabulate>=0.8.9
Requires-Dist: biopython>=1.79
Requires-Dist: pandas>=1.4.2
Requires-Dist: cgecore>=2.0.1
